genome/__init__.py
genome/genome.py
genome/genotype.py
genome/snp.py
genome/utils.py
genome/version.py
genome/tests/__init__.py
genome/tests/conftest.py
genome/tests/test_genome.py
genome/tests/tt.txt
genome_py-0.1.4.data/scripts/genome
genome_py-0.1.4.dist-info/LICENSE
genome_py-0.1.4.dist-info/METADATA
genome_py-0.1.4.dist-info/WHEEL
genome_py-0.1.4.dist-info/top_level.txt
genome_py-0.1.4.dist-info/RECORD
